pynite_tools/__init__.py
pynite_tools/combos.py
pynite_tools/envelope.py
pynite_tools/reports.py
pynite_tools/serialize.py
pynite_tools/visualize.py
pynite_tools-0.6.5.dist-info/entry_points.txt
pynite_tools-0.6.5.dist-info/licenses/LICENSE
pynite_tools-0.6.5.dist-info/WHEEL
pynite_tools-0.6.5.dist-info/METADATA
pynite_tools-0.6.5.dist-info/RECORD
