Metadata-Version: 2.4
Name: pynite-tools
Version: 0.6.5
Summary: pynite-tools: A series of functions that enhance the capabilities of PyniteFEA.
Author-email: Connor Ferster <connorferster@gmail.com>
Requires-Python: >=3.11
License-File: LICENSE
Requires-Dist: numpy>=2.0.2
Requires-Dist: plotly>=6.2.0
Requires-Dist: plotly-3d-primitives>=0.4.0
Requires-Dist: pydantic_core==2.27.2
Requires-Dist: pydantic==2.10.6
Requires-Dist: pynitefea==1.1.2
Requires-Dist: deepmerge>=2.0
